{
  "info": [
    {
      "name": "Data",
      "description": "Exported from Superb AI Suite",
      "url": "https://www.superb-ai.com",
      "date_created": "2022-01-22 13:26:40.204292"
    }
  ],
  "license": [
    {
      "name": "",
      "url": ""
    }
  ],
  "images": [
    {
      "id": "1121159_591",
      "width": 2800,
      "height": 2100,
      "file_name": "1121159_591.jpg",
      "license": "",
      "date_created": "2022-01-22 13:26:40.204387"
    }
  ],
  "annotations": [
    {
      "id": "218a89ea-9110-4df7-8fba-d747c3f3d63d",
      "image_id": "1121159_591",
      "category_id": 104,
      "segmentation": [
        {
          "x": 1635.6845393520312,
          "y": 754.3388545931914
        },
        {
          "x": 1631.8588772789308,
          "y": 738.0420219454777
        },
        {
          "x": 1630.718520856255,
          "y": 720.0574727555569
        },
        {
          "x": 1637.2688948461184,
          "y": 696.555176650282
        },
        {
          "x": 1650.8007178489404,
          "y": 680.5589315169966
        },
        {
          "x": 1667.550176387138,
          "y": 666.543462268448
        },
        {
          "x": 1691.5156790950668,
          "y": 657.9227357352278
        },
        {
          "x": 1712.5025638930733,
          "y": 652.7182296355352
        },
        {
          "x": 1737.7204977048636,
          "y": 655.0637192442488
        },
        {
          "x": 1755.0121831720883,
          "y": 664.2531941454919
        },
        {
          "x": 1775.3700407211309,
          "y": 680.1621101887044
        },
        {
          "x": 1786.7734056117044,
          "y": 695.1663868031878
        },
        {
          "x": 1791.1881188230711,
          "y": 704.6378486905711
        },
        {
          "x": 1793.6640614155015,
          "y": 716.791940348356
        },
        {
          "x": 1792.1222707021302,
          "y": 735.0622195853091
        },
        {
          "x": 1786.4616963653043,
          "y": 754.6633817625502
        },
        {
          "x": 1771.440232414079,
          "y": 774.7027429579084
        },
        {
          "x": 1747.25080639843,
          "y": 790.5348832044881
        },
        {
          "x": 1734.1869862012777,
          "y": 795.4804643328346
        },
        {
          "x": 1711.058573883084,
          "y": 797.4744686357802
        },
        {
          "x": 1688.2894439931886,
          "y": 796.2583126930284
        },
        {
          "x": 1673.315416603442,
          "y": 790.8346088883505
        },
        {
          "x": 1657.9060848407225,
          "y": 781.7602220528962
        },
        {
          "x": 1649.8380732934002,
          "y": 773.0433269423808
        },
        {
          "x": 1635.6845393520312,
          "y": 754.3388545931914
        }
      ],
      "bbox": [
        1630.718520856255,
        652.7182296355352,
        162.9455405592464,
        144.75623900024505
      ],
      "area": 23587.383613218397,
      "isSmallType": "Y"
    },
    {
      "id": "ae27c37e-f92d-45f4-9b61-b85ac1e6676e",
      "image_id": "1121159_591",
      "category_id": 104,
      "segmentation": [
        {
          "x": 2010.619957396703,
          "y": 733.7807738571186
        },
        {
          "x": 2008.2571372807843,
          "y": 722.0669262954137
        },
        {
          "x": 2007.8455019252258,
          "y": 704.4661466454788
        },
        {
          "x": 2011.8423370359876,
          "y": 682.7463823182242
        },
        {
          "x": 2018.2666627389904,
          "y": 665.1289007651015
        },
        {
          "x": 2033.2092294597153,
          "y": 644.3608745275931
        },
        {
          "x": 2054.2080352324915,
          "y": 629.0379703203281
        },
        {
          "x": 2067.7015194574,
          "y": 626.3191583936865
        },
        {
          "x": 2089.673351486688,
          "y": 622.2333695289292
        },
        {
          "x": 2111.425739643519,
          "y": 626.2976414337267
        },
        {
          "x": 2142.1368165165836,
          "y": 638.4434349468341
        },
        {
          "x": 2156.25050709293,
          "y": 649.908038322518
        },
        {
          "x": 2174.9480277193775,
          "y": 672.4905531865288
        },
        {
          "x": 2186.4605684691237,
          "y": 697.969641889503
        },
        {
          "x": 2186.1418387500084,
          "y": 716.9978050807082
        },
        {
          "x": 2166.628649586311,
          "y": 754.6433748814201
        },
        {
          "x": 2142.56651093496,
          "y": 777.8680472439135
        },
        {
          "x": 2115.8246839932017,
          "y": 787.1010174014133
        },
        {
          "x": 2099.2632390273784,
          "y": 787.4526205426807
        },
        {
          "x": 2083.258739094754,
          "y": 785.7589997208634
        },
        {
          "x": 2069.7511424896306,
          "y": 782.067525526883
        },
        {
          "x": 2057.4815458591515,
          "y": 779.2834555413975
        },
        {
          "x": 2046.2215303978273,
          "y": 774.6980863370795
        },
        {
          "x": 2037.2921896086152,
          "y": 769.7662306392951
        },
        {
          "x": 2028.2436475651452,
          "y": 760.4664632687349
        },
        {
          "x": 2020.0606093765316,
          "y": 747.4217360951687
        },
        {
          "x": 2010.619957396703,
          "y": 733.7807738571186
        }
      ],
      "bbox": [
        2007.8455019252258,
        622.2333695289292,
        178.6150665438979,
        165.21925101375155
      ],
      "area": 29510.647514154203,
      "isSmallType": "Y"
    }
  ],
  "categories": [
    {
      "id": "500cb699-4091-4a67-9d3f-e4dfbfb57399",
      "class_id": 85,
      "class_name": "매실",
      "superclass_id": 591,
      "superclass_name": "과일"
    },
    {
      "id": "b59fe2ea-5c83-4841-a6a3-70838bf758f8",
      "class_id": 86,
      "class_name": "무화과",
      "superclass_id": 591,
      "superclass_name": "과일"
    },
    {
      "id": "d400adc3-a14e-4e21-838d-e3be3d87b159",
      "class_id": 87,
      "class_name": "체리",
      "superclass_id": 591,
      "superclass_name": "과일"
    },
    {
      "id": "0b4ef7df-31b0-4a58-9d1d-67ae47ccd811",
      "class_id": 88,
      "class_name": "복분자",
      "superclass_id": 591,
      "superclass_name": "과일"
    },
    {
      "id": "2b6d721d-7d03-4f53-809c-fbf45b4baf49",
      "class_id": 89,
      "class_name": "복숭아",
      "superclass_id": 591,
      "superclass_name": "과일"
    },
    {
      "id": "3739fc7a-9c1e-48bb-8975-5c5b03542fdd",
      "class_id": 90,
      "class_name": "천도복숭아",
      "superclass_id": 591,
      "superclass_name": "과일"
    },
    {
      "id": "f21a933b-5d7a-4252-8036-bcd93ab13acf",
      "class_id": 91,
      "class_name": "블랙베리",
      "superclass_id": 591,
      "superclass_name": "과일"
    },
    {
      "id": "4a78c12b-c5ad-409b-8095-e17056af4d1b",
      "class_id": 92,
      "class_name": "블루베리",
      "superclass_id": 591,
      "superclass_name": "과일"
    },
    {
      "id": "888c6543-c212-4c0b-805d-7c396106102b",
      "class_id": 93,
      "class_name": "산딸기",
      "superclass_id": 591,
      "superclass_name": "과일"
    },
    {
      "id": "e1431885-491a-4a95-b2a1-1b34cd576963",
      "class_id": 94,
      "class_name": "자두",
      "superclass_id": 591,
      "superclass_name": "과일"
    },
    {
      "id": "1b7fcf51-bdad-4215-a645-c92f892e5a8d",
      "class_id": 95,
      "class_name": "포도(송이)",
      "superclass_id": 591,
      "superclass_name": "과일"
    },
    {
      "id": "2a3a9c78-9978-4176-9f88-275765d1b8d7",
      "class_id": 96,
      "class_name": "감",
      "superclass_id": 591,
      "superclass_name": "과일"
    },
    {
      "id": "727be456-cd25-42f6-a15b-370c7fe7ba9f",
      "class_id": 97,
      "class_name": "대추",
      "superclass_id": 591,
      "superclass_name": "과일"
    },
    {
      "id": "86bdba0d-fcf2-44f8-9d70-d7a02e74f4e7",
      "class_id": 98,
      "class_name": "머루(송이)",
      "superclass_id": 591,
      "superclass_name": "과일"
    },
    {
      "id": "1f306b86-22a4-4ae4-b263-9799fe7077c3",
      "class_id": 99,
      "class_name": "모과",
      "superclass_id": 591,
      "superclass_name": "과일"
    },
    {
      "id": "8ee790b3-c5cb-4101-b4aa-a6647c5a52da",
      "class_id": 100,
      "class_name": "배",
      "superclass_id": 591,
      "superclass_name": "과일"
    },
    {
      "id": "ad722f43-6b14-4981-8ccd-7297ac8c0ded",
      "class_id": 101,
      "class_name": "사과",
      "superclass_id": 591,
      "superclass_name": "과일"
    },
    {
      "id": "33267a3e-db42-4743-b39e-a612f239ea9f",
      "class_id": 102,
      "class_name": "석류",
      "superclass_id": 591,
      "superclass_name": "과일"
    },
    {
      "id": "bd51c740-e9b3-4813-b90b-ff75c8a48da7",
      "class_id": 103,
      "class_name": "유자",
      "superclass_id": 591,
      "superclass_name": "과일"
    },
    {
      "id": "9356e0c7-0ad3-4d96-aa76-debcf0e5417f",
      "class_id": 104,
      "class_name": "귤",
      "superclass_id": 591,
      "superclass_name": "과일"
    },
    {
      "id": "1a05d6a2-1d37-4ebc-919d-201e812412f1",
      "class_id": 105,
      "class_name": "천혜향",
      "superclass_id": 591,
      "superclass_name": "과일"
    },
    {
      "id": "72b57438-5f37-44d1-b58d-7226008b29d1",
      "class_id": 106,
      "class_name": "한라봉",
      "superclass_id": 591,
      "superclass_name": "과일"
    },
    {
      "id": "f78899a4-ffed-4bef-a981-7d475fe89561",
      "class_id": 107,
      "class_name": "딸기",
      "superclass_id": 591,
      "superclass_name": "과일"
    },
    {
      "id": "924587db-2bf3-479c-9698-5a6d4e8d084a",
      "class_id": 108,
      "class_name": "수박",
      "superclass_id": 591,
      "superclass_name": "과일"
    },
    {
      "id": "0521bb01-1539-4789-87c6-1f24ab7c8367",
      "class_id": 109,
      "class_name": "참외",
      "superclass_id": 591,
      "superclass_name": "과일"
    },
    {
      "id": "0a02e76e-2c0c-4d15-9305-4564e9e105ef",
      "class_id": 110,
      "class_name": "멜론",
      "superclass_id": 591,
      "superclass_name": "과일"
    },
    {
      "id": "cfeb4092-a390-45b4-9790-f9b4bad4f20f",
      "class_id": 111,
      "class_name": "파인애플",
      "superclass_id": 591,
      "superclass_name": "과일"
    },
    {
      "id": "afd5d390-0f4d-4fc9-8b89-07ec1c60a9a9",
      "class_id": 112,
      "class_name": "바나나",
      "superclass_id": 591,
      "superclass_name": "과일"
    },
    {
      "id": "4ac62f45-61c2-49f2-8929-40411f072323",
      "class_id": 113,
      "class_name": "용과",
      "superclass_id": 591,
      "superclass_name": "과일"
    },
    {
      "id": "660477c3-357f-462b-8e89-6dcf1a82575d",
      "class_id": 114,
      "class_name": "아보카도",
      "superclass_id": 591,
      "superclass_name": "과일"
    },
    {
      "id": "134caecc-dd08-4864-913f-107a5e3ae5ba",
      "class_id": 115,
      "class_name": "자몽",
      "superclass_id": 591,
      "superclass_name": "과일"
    },
    {
      "id": "e5ac9730-1541-4b90-b505-752fc65e7327",
      "class_id": 116,
      "class_name": "두리안",
      "superclass_id": 591,
      "superclass_name": "과일"
    },
    {
      "id": "325e6e93-e20b-4c41-ae40-9be5496d894e",
      "class_id": 117,
      "class_name": "망고스틴",
      "superclass_id": 591,
      "superclass_name": "과일"
    },
    {
      "id": "132e28d3-c644-468e-ab78-028337f21ce8",
      "class_id": 118,
      "class_name": "망고",
      "superclass_id": 591,
      "superclass_name": "과일"
    },
    {
      "id": "5d931aef-e541-4600-87fa-a38e105b6415",
      "class_id": 119,
      "class_name": "구아바",
      "superclass_id": 591,
      "superclass_name": "과일"
    },
    {
      "id": "8a0f7d06-318b-4b43-9a22-1e853d12a7dd",
      "class_id": 120,
      "class_name": "리치",
      "superclass_id": 591,
      "superclass_name": "과일"
    },
    {
      "id": "9d74530c-4bc4-407f-8d59-1a2aafcae55e",
      "class_id": 121,
      "class_name": "파파야",
      "superclass_id": 591,
      "superclass_name": "과일"
    },
    {
      "id": "2458263a-4b1e-4ea6-b02a-0e82cbdd78d2",
      "class_id": 122,
      "class_name": "람부탄",
      "superclass_id": 591,
      "superclass_name": "과일"
    },
    {
      "id": "b1700308-3cf8-4f45-b466-d7770566f300",
      "class_id": 123,
      "class_name": "패션후르츠",
      "superclass_id": 591,
      "superclass_name": "과일"
    },
    {
      "id": "c94f757b-ae9a-4f22-a3eb-b156a8f3e965",
      "class_id": 124,
      "class_name": "레몬",
      "superclass_id": 591,
      "superclass_name": "과일"
    },
    {
      "id": "54fe9d33-3136-4e25-8090-697b742cea4e",
      "class_id": 125,
      "class_name": "키위",
      "superclass_id": 591,
      "superclass_name": "과일"
    }
  ]
}