{
  "info": [
    {
      "name": "Data",
      "description": "Exported from Superb AI Suite",
      "url": "https://www.superb-ai.com",
      "date_created": "2022-01-22 13:26:41.784116"
    }
  ],
  "license": [
    {
      "name": "",
      "url": ""
    }
  ],
  "images": [
    {
      "id": "973971_591",
      "width": 2800,
      "height": 2100,
      "file_name": "973971_591.jpg",
      "license": "",
      "date_created": "2022-01-22 13:26:41.784184"
    }
  ],
  "annotations": [
    {
      "id": "e63d1d1e-4975-4f8f-8e90-eee6655feb15",
      "image_id": "973971_591",
      "category_id": 104,
      "segmentation": [
        {
          "x": 1161.502918301785,
          "y": 1305.9038698425838
        },
        {
          "x": 1142.4850106652173,
          "y": 1293.332707309628
        },
        {
          "x": 1129.9138659687137,
          "y": 1282.3732600261171
        },
        {
          "x": 1122.8224513269981,
          "y": 1269.1574396745903
        },
        {
          "x": 1119.9214264482357,
          "y": 1250.139569846067
        },
        {
          "x": 1121.5331110351628,
          "y": 1232.4110402470394
        },
        {
          "x": 1124.4341359139253,
          "y": 1215.6495188941778
        },
        {
          "x": 1129.2691896747071,
          "y": 1201.466702592662
        },
        {
          "x": 1136.3606043164225,
          "y": 1191.4742512591401
        },
        {
          "x": 1146.997720130907,
          "y": 1179.2254514499564
        },
        {
          "x": 1161.8252257083443,
          "y": 1166.0096495426951
        },
        {
          "x": 1171.1729889348157,
          "y": 1161.1745960156877
        },
        {
          "x": 1187.289847100266,
          "y": 1156.6618683239215
        },
        {
          "x": 1201.4726763836968,
          "y": 1154.0831755687527
        },
        {
          "x": 1219.5235634311666,
          "y": 1154.405513700171
        },
        {
          "x": 1235.9627412993536,
          "y": 1159.5629053585967
        },
        {
          "x": 1253.368939756639,
          "y": 1168.9106742811935
        },
        {
          "x": 1267.8741010389842,
          "y": 1185.0275193712187
        },
        {
          "x": 1282.701594320244,
          "y": 1205.334741725415
        },
        {
          "x": 1288.8260006690386,
          "y": 1223.3856156039492
        },
        {
          "x": 1287.5366480810258,
          "y": 1243.3704936786387
        },
        {
          "x": 1281.4122417322312,
          "y": 1260.7767158866905
        },
        {
          "x": 1270.7751382139245,
          "y": 1277.8605446305278
        },
        {
          "x": 1262.3943832803736,
          "y": 1293.6550577372232
        },
        {
          "x": 1250.4679025816988,
          "y": 1303.9698287578976
        },
        {
          "x": 1226.2926337777901,
          "y": 1313.9622923875963
        },
        {
          "x": 1203.4067175618939,
          "y": 1316.2186408632583
        },
        {
          "x": 1181.4877973427413,
          "y": 1313.6399358119127
        },
        {
          "x": 1161.502918301785,
          "y": 1305.9038698425838
        }
      ],
      "bbox": [
        1119.9214264482357,
        1154.0831755687527,
        168.90457422080294,
        162.1354652945056
      ],
      "area": 27385.42173166024,
      "isSmallType": "Y"
    },
    {
      "id": "222d96c9-fe27-46c4-8275-baa178b881ac",
      "image_id": "973971_591",
      "category_id": 104,
      "segmentation": [
        {
          "x": 1401.0636330370814,
          "y": 1112.5300357511026
        },
        {
          "x": 1383.481557863194,
          "y": 1104.5381904835403
        },
        {
          "x": 1373.8913258027278,
          "y": 1095.7471228351037
        },
        {
          "x": 1366.9650278971626,
          "y": 1083.7593282580397
        },
        {
          "x": 1361.3707275555876,
          "y": 1070.972349408274
        },
        {
          "x": 1358.706773076327,
          "y": 1056.3206004807512
        },
        {
          "x": 1358.706773076327,
          "y": 1041.9352429234027
        },
        {
          "x": 1359.772358932903,
          "y": 1029.414655443811
        },
        {
          "x": 1362.969096178272,
          "y": 1020.6236081197333
        },
        {
          "x": 1368.297005136793,
          "y": 1010.7669749906003
        },
        {
          "x": 1375.4896944254122,
          "y": 1001.7095413774381
        },
        {
          "x": 1386.6782951085627,
          "y": 991.053713813424
        },
        {
          "x": 1397.334113025605,
          "y": 983.8610350347496
        },
        {
          "x": 1406.1251709369085,
          "y": 978.5331288743772
        },
        {
          "x": 1415.4490116143204,
          "y": 974.0044069867064
        },
        {
          "x": 1427.703198154047,
          "y": 972.1396369089495
        },
        {
          "x": 1440.2237760768273,
          "y": 972.6724298114771
        },
        {
          "x": 1450.8795939938695,
          "y": 976.4019598048117
        },
        {
          "x": 1465.2649319223888,
          "y": 984.6602218479964
        },
        {
          "x": 1479.9166815583217,
          "y": 994.5168498960396
        },
        {
          "x": 1487.6421536130492,
          "y": 1005.4390739113175
        },
        {
          "x": 1491.9044767149942,
          "y": 1022.7547771892989
        },
        {
          "x": 1493.5028656620382,
          "y": 1041.668843931594
        },
        {
          "x": 1493.7692570450922,
          "y": 1060.5829157549788
        },
        {
          "x": 1491.6380853319401,
          "y": 1073.369904766924
        },
        {
          "x": 1485.2445905168427,
          "y": 1083.2265277338777
        },
        {
          "x": 1476.1871615468447,
          "y": 1094.6815395705935
        },
        {
          "x": 1464.1993663901721,
          "y": 1104.8045640699006
        },
        {
          "x": 1450.0803995203473,
          "y": 1112.5300357511026
        },
        {
          "x": 1434.0966726447841,
          "y": 1116.2595759066164
        },
        {
          "x": 1419.4449230088512,
          "y": 1115.9931642120835
        },
        {
          "x": 1401.0636330370814,
          "y": 1112.5300357511026
        }
      ],
      "bbox": [
        1358.706773076327,
        972.1396369089495,
        135.06248396876526,
        144.11993899766696
      ],
      "area": 19465.196950451824,
      "isSmallType": "Y"
    }
  ],
  "categories": [
    {
      "id": "500cb699-4091-4a67-9d3f-e4dfbfb57399",
      "class_id": 85,
      "class_name": "매실",
      "superclass_id": 591,
      "superclass_name": "과일"
    },
    {
      "id": "b59fe2ea-5c83-4841-a6a3-70838bf758f8",
      "class_id": 86,
      "class_name": "무화과",
      "superclass_id": 591,
      "superclass_name": "과일"
    },
    {
      "id": "d400adc3-a14e-4e21-838d-e3be3d87b159",
      "class_id": 87,
      "class_name": "체리",
      "superclass_id": 591,
      "superclass_name": "과일"
    },
    {
      "id": "0b4ef7df-31b0-4a58-9d1d-67ae47ccd811",
      "class_id": 88,
      "class_name": "복분자",
      "superclass_id": 591,
      "superclass_name": "과일"
    },
    {
      "id": "2b6d721d-7d03-4f53-809c-fbf45b4baf49",
      "class_id": 89,
      "class_name": "복숭아",
      "superclass_id": 591,
      "superclass_name": "과일"
    },
    {
      "id": "3739fc7a-9c1e-48bb-8975-5c5b03542fdd",
      "class_id": 90,
      "class_name": "천도복숭아",
      "superclass_id": 591,
      "superclass_name": "과일"
    },
    {
      "id": "f21a933b-5d7a-4252-8036-bcd93ab13acf",
      "class_id": 91,
      "class_name": "블랙베리",
      "superclass_id": 591,
      "superclass_name": "과일"
    },
    {
      "id": "4a78c12b-c5ad-409b-8095-e17056af4d1b",
      "class_id": 92,
      "class_name": "블루베리",
      "superclass_id": 591,
      "superclass_name": "과일"
    },
    {
      "id": "888c6543-c212-4c0b-805d-7c396106102b",
      "class_id": 93,
      "class_name": "산딸기",
      "superclass_id": 591,
      "superclass_name": "과일"
    },
    {
      "id": "e1431885-491a-4a95-b2a1-1b34cd576963",
      "class_id": 94,
      "class_name": "자두",
      "superclass_id": 591,
      "superclass_name": "과일"
    },
    {
      "id": "1b7fcf51-bdad-4215-a645-c92f892e5a8d",
      "class_id": 95,
      "class_name": "포도(송이)",
      "superclass_id": 591,
      "superclass_name": "과일"
    },
    {
      "id": "2a3a9c78-9978-4176-9f88-275765d1b8d7",
      "class_id": 96,
      "class_name": "감",
      "superclass_id": 591,
      "superclass_name": "과일"
    },
    {
      "id": "727be456-cd25-42f6-a15b-370c7fe7ba9f",
      "class_id": 97,
      "class_name": "대추",
      "superclass_id": 591,
      "superclass_name": "과일"
    },
    {
      "id": "86bdba0d-fcf2-44f8-9d70-d7a02e74f4e7",
      "class_id": 98,
      "class_name": "머루(송이)",
      "superclass_id": 591,
      "superclass_name": "과일"
    },
    {
      "id": "1f306b86-22a4-4ae4-b263-9799fe7077c3",
      "class_id": 99,
      "class_name": "모과",
      "superclass_id": 591,
      "superclass_name": "과일"
    },
    {
      "id": "8ee790b3-c5cb-4101-b4aa-a6647c5a52da",
      "class_id": 100,
      "class_name": "배",
      "superclass_id": 591,
      "superclass_name": "과일"
    },
    {
      "id": "ad722f43-6b14-4981-8ccd-7297ac8c0ded",
      "class_id": 101,
      "class_name": "사과",
      "superclass_id": 591,
      "superclass_name": "과일"
    },
    {
      "id": "33267a3e-db42-4743-b39e-a612f239ea9f",
      "class_id": 102,
      "class_name": "석류",
      "superclass_id": 591,
      "superclass_name": "과일"
    },
    {
      "id": "bd51c740-e9b3-4813-b90b-ff75c8a48da7",
      "class_id": 103,
      "class_name": "유자",
      "superclass_id": 591,
      "superclass_name": "과일"
    },
    {
      "id": "9356e0c7-0ad3-4d96-aa76-debcf0e5417f",
      "class_id": 104,
      "class_name": "귤",
      "superclass_id": 591,
      "superclass_name": "과일"
    },
    {
      "id": "1a05d6a2-1d37-4ebc-919d-201e812412f1",
      "class_id": 105,
      "class_name": "천혜향",
      "superclass_id": 591,
      "superclass_name": "과일"
    },
    {
      "id": "72b57438-5f37-44d1-b58d-7226008b29d1",
      "class_id": 106,
      "class_name": "한라봉",
      "superclass_id": 591,
      "superclass_name": "과일"
    },
    {
      "id": "f78899a4-ffed-4bef-a981-7d475fe89561",
      "class_id": 107,
      "class_name": "딸기",
      "superclass_id": 591,
      "superclass_name": "과일"
    },
    {
      "id": "924587db-2bf3-479c-9698-5a6d4e8d084a",
      "class_id": 108,
      "class_name": "수박",
      "superclass_id": 591,
      "superclass_name": "과일"
    },
    {
      "id": "0521bb01-1539-4789-87c6-1f24ab7c8367",
      "class_id": 109,
      "class_name": "참외",
      "superclass_id": 591,
      "superclass_name": "과일"
    },
    {
      "id": "0a02e76e-2c0c-4d15-9305-4564e9e105ef",
      "class_id": 110,
      "class_name": "멜론",
      "superclass_id": 591,
      "superclass_name": "과일"
    },
    {
      "id": "cfeb4092-a390-45b4-9790-f9b4bad4f20f",
      "class_id": 111,
      "class_name": "파인애플",
      "superclass_id": 591,
      "superclass_name": "과일"
    },
    {
      "id": "afd5d390-0f4d-4fc9-8b89-07ec1c60a9a9",
      "class_id": 112,
      "class_name": "바나나",
      "superclass_id": 591,
      "superclass_name": "과일"
    },
    {
      "id": "4ac62f45-61c2-49f2-8929-40411f072323",
      "class_id": 113,
      "class_name": "용과",
      "superclass_id": 591,
      "superclass_name": "과일"
    },
    {
      "id": "660477c3-357f-462b-8e89-6dcf1a82575d",
      "class_id": 114,
      "class_name": "아보카도",
      "superclass_id": 591,
      "superclass_name": "과일"
    },
    {
      "id": "134caecc-dd08-4864-913f-107a5e3ae5ba",
      "class_id": 115,
      "class_name": "자몽",
      "superclass_id": 591,
      "superclass_name": "과일"
    },
    {
      "id": "e5ac9730-1541-4b90-b505-752fc65e7327",
      "class_id": 116,
      "class_name": "두리안",
      "superclass_id": 591,
      "superclass_name": "과일"
    },
    {
      "id": "325e6e93-e20b-4c41-ae40-9be5496d894e",
      "class_id": 117,
      "class_name": "망고스틴",
      "superclass_id": 591,
      "superclass_name": "과일"
    },
    {
      "id": "132e28d3-c644-468e-ab78-028337f21ce8",
      "class_id": 118,
      "class_name": "망고",
      "superclass_id": 591,
      "superclass_name": "과일"
    },
    {
      "id": "5d931aef-e541-4600-87fa-a38e105b6415",
      "class_id": 119,
      "class_name": "구아바",
      "superclass_id": 591,
      "superclass_name": "과일"
    },
    {
      "id": "8a0f7d06-318b-4b43-9a22-1e853d12a7dd",
      "class_id": 120,
      "class_name": "리치",
      "superclass_id": 591,
      "superclass_name": "과일"
    },
    {
      "id": "9d74530c-4bc4-407f-8d59-1a2aafcae55e",
      "class_id": 121,
      "class_name": "파파야",
      "superclass_id": 591,
      "superclass_name": "과일"
    },
    {
      "id": "2458263a-4b1e-4ea6-b02a-0e82cbdd78d2",
      "class_id": 122,
      "class_name": "람부탄",
      "superclass_id": 591,
      "superclass_name": "과일"
    },
    {
      "id": "b1700308-3cf8-4f45-b466-d7770566f300",
      "class_id": 123,
      "class_name": "패션후르츠",
      "superclass_id": 591,
      "superclass_name": "과일"
    },
    {
      "id": "c94f757b-ae9a-4f22-a3eb-b156a8f3e965",
      "class_id": 124,
      "class_name": "레몬",
      "superclass_id": 591,
      "superclass_name": "과일"
    },
    {
      "id": "54fe9d33-3136-4e25-8090-697b742cea4e",
      "class_id": 125,
      "class_name": "키위",
      "superclass_id": 591,
      "superclass_name": "과일"
    }
  ]
}