{
  "info": [
    {
      "name": "Data",
      "description": "Exported from Superb AI Suite",
      "url": "https://www.superb-ai.com",
      "date_created": "2022-01-22 13:26:51.878316"
    }
  ],
  "license": [
    {
      "name": "",
      "url": ""
    }
  ],
  "images": [
    {
      "id": "1465441_593",
      "width": 2800,
      "height": 2100,
      "file_name": "1465441_593.jpg",
      "license": "",
      "date_created": "2022-01-22 13:26:51.878403"
    }
  ],
  "annotations": [
    {
      "id": "4d44c0e3-a142-4c75-b4db-3b818a290ddb",
      "image_id": "1465441_593",
      "category_id": 182,
      "segmentation": [
        {
          "x": 1492.594441668076,
          "y": 1191.186929823666
        },
        {
          "x": 1506.2459525391946,
          "y": 1192.5218015367636
        },
        {
          "x": 1519.63349875335,
          "y": 1201.6163853605726
        },
        {
          "x": 1524.860403951131,
          "y": 1216.0530191236103
        },
        {
          "x": 1526.9883485423054,
          "y": 1230.4896528866477
        },
        {
          "x": 1538.4422732010044,
          "y": 1270.980438819846
        },
        {
          "x": 1533.9535203677235,
          "y": 1294.980540411372
        },
        {
          "x": 1533.611331632089,
          "y": 1320.8965660566146
        },
        {
          "x": 1543.125332426582,
          "y": 1332.5653129136263
        },
        {
          "x": 1567.9904924353177,
          "y": 1340.8598835499254
        },
        {
          "x": 1568.6993468310616,
          "y": 1346.3433027072667
        },
        {
          "x": 1536.2337800000269,
          "y": 1336.5023807287255
        },
        {
          "x": 1514.1767978419066,
          "y": 1305.8546193929235
        },
        {
          "x": 1502.2514205445207,
          "y": 1287.7285247631505
        },
        {
          "x": 1487.4715744949278,
          "y": 1260.9260705145775
        },
        {
          "x": 1470.3645343658293,
          "y": 1245.600653104136
        },
        {
          "x": 1462.1749171535043,
          "y": 1215.8828262742009
        },
        {
          "x": 1473.1251231280162,
          "y": 1202.366160381745
        },
        {
          "x": 1459.9259915351256,
          "y": 1190.9161746505722
        },
        {
          "x": 1450.337328354054,
          "y": 1174.6113030089332
        },
        {
          "x": 1444.4654184712688,
          "y": 1161.9904248702258
        },
        {
          "x": 1451.4803985079147,
          "y": 1157.5419047272944
        },
        {
          "x": 1466.9556288778601,
          "y": 1147.407459375709
        },
        {
          "x": 1492.594441668076,
          "y": 1191.186929823666
        }
      ],
      "bbox": [
        1444.4654184712688,
        1147.407459375709,
        124.2339283597928,
        198.93584333155763
      ],
      "area": 24714.581308647696,
      "isSmallType": "Y"
    },
    {
      "id": "ebfbbfb2-f47d-46c3-8823-8e509686cbdb",
      "image_id": "1465441_593",
      "category_id": 182,
      "segmentation": [
        {
          "x": 1605.8621974648167,
          "y": 1187.1363594250417
        },
        {
          "x": 1603.1653197181945,
          "y": 1167.3269103590271
        },
        {
          "x": 1619.8950202065193,
          "y": 1165.4076132386508
        },
        {
          "x": 1627.5308664199215,
          "y": 1168.3939478194195
        },
        {
          "x": 1623.8168981207484,
          "y": 1191.4380402121528
        },
        {
          "x": 1634.7409073506158,
          "y": 1210.025523759341
        },
        {
          "x": 1632.4917154375012,
          "y": 1232.9712091514116
        },
        {
          "x": 1622.7525402525748,
          "y": 1270.4759046073493
        },
        {
          "x": 1616.6851478424094,
          "y": 1285.8959787009178
        },
        {
          "x": 1609.4325885188825,
          "y": 1300.198258447801
        },
        {
          "x": 1606.3528455157168,
          "y": 1296.9474210724334
        },
        {
          "x": 1590.731330570849,
          "y": 1269.5382364585168
        },
        {
          "x": 1589.5040114199173,
          "y": 1240.628436623311
        },
        {
          "x": 1584.28051812344,
          "y": 1218.8433746480077
        },
        {
          "x": 1588.940742575414,
          "y": 1195.7690300636737
        },
        {
          "x": 1605.8621974648167,
          "y": 1187.1363594250417
        }
      ],
      "bbox": [
        1584.28051812344,
        1165.4076132386508,
        50.46038922717571,
        134.79064520915017
      ],
      "area": 6801.588421435865,
      "isSmallType": "Y"
    },
    {
      "id": "a3c1f842-4259-47e5-9cd5-522723ef7d50",
      "image_id": "1465441_593",
      "category_id": 182,
      "segmentation": [
        {
          "x": 1884.1935846959805,
          "y": 1298.1300819975838
        },
        {
          "x": 1909.9874697874034,
          "y": 1268.7931010229586
        },
        {
          "x": 1926.459663266111,
          "y": 1287.86984012215
        },
        {
          "x": 1908.0637122327894,
          "y": 1307.0872216767364
        },
        {
          "x": 1902.4175093299093,
          "y": 1320.4327821055304
        },
        {
          "x": 1898.2799992532834,
          "y": 1342.700236995571
        },
        {
          "x": 1876.0564830246983,
          "y": 1365.5128194019671
        },
        {
          "x": 1847.8774181750266,
          "y": 1379.0167142426965
        },
        {
          "x": 1827.45627348394,
          "y": 1381.2574734921961
        },
        {
          "x": 1799.2513669492719,
          "y": 1384.8748655720276
        },
        {
          "x": 1786.4530089339141,
          "y": 1395.5701831162496
        },
        {
          "x": 1778.4114515947508,
          "y": 1390.7794631416084
        },
        {
          "x": 1794.2299358792743,
          "y": 1370.1285282568144
        },
        {
          "x": 1816.833277166168,
          "y": 1346.5900596862118
        },
        {
          "x": 1834.4351151058013,
          "y": 1323.7466869509358
        },
        {
          "x": 1854.8204986329788,
          "y": 1299.1512058071994
        },
        {
          "x": 1884.1935846959805,
          "y": 1298.1300819975838
        }
      ],
      "bbox": [
        1778.4114515947508,
        1268.7931010229586,
        148.04821167136015,
        126.77708209329103
      ],
      "area": 18769.120284824952,
      "isSmallType": "Y"
    },
    {
      "id": "7b277e84-e341-401c-9b0b-42dc4540a63d",
      "image_id": "1465441_593",
      "category_id": 182,
      "segmentation": [
        {
          "x": 2067.0526542243083,
          "y": 1365.3844597912823
        },
        {
          "x": 2072.1048867187583,
          "y": 1357.259518901982
        },
        {
          "x": 2078.703803421785,
          "y": 1362.2861538217228
        },
        {
          "x": 2082.125735160585,
          "y": 1370.6699110034413
        },
        {
          "x": 2076.4795766401608,
          "y": 1380.5935285932057
        },
        {
          "x": 2070.3500266003903,
          "y": 1398.2318711266742
        },
        {
          "x": 2052.799605736014,
          "y": 1414.7559699099404
        },
        {
          "x": 2026.2470025595496,
          "y": 1427.7582764236931
        },
        {
          "x": 2006.4035842980031,
          "y": 1439.1553582672623
        },
        {
          "x": 1987.7833687145958,
          "y": 1452.994984196733
        },
        {
          "x": 1975.928193366962,
          "y": 1459.4258911213064
        },
        {
          "x": 1973.0195447316132,
          "y": 1466.2697767993654
        },
        {
          "x": 1969.2554242571784,
          "y": 1469.0073310705889
        },
        {
          "x": 1968.3420998867177,
          "y": 1444.4755942293452
        },
        {
          "x": 1979.241676574566,
          "y": 1416.4031803835414
        },
        {
          "x": 2000.3051907423328,
          "y": 1394.084064314666
        },
        {
          "x": 2029.0023098094746,
          "y": 1367.4865016744182
        },
        {
          "x": 2046.9235017111384,
          "y": 1359.4784197918802
        },
        {
          "x": 2067.0526542243083,
          "y": 1365.3844597912823
        }
      ],
      "bbox": [
        1968.3420998867177,
        1357.259518901982,
        113.78363527386728,
        111.74781216860697
      ],
      "area": 12715.072302445404,
      "isSmallType": "Y"
    }
  ],
  "categories": [
    {
      "id": "d07035dc-9c6e-4a7a-8443-630b8ecce69e",
      "class_id": 175,
      "class_name": "토마토",
      "superclass_id": 593,
      "superclass_name": "채소"
    },
    {
      "id": "e5b10eb3-3a56-4893-90e0-b03d09056ab9",
      "class_id": 180,
      "class_name": "방울토마토",
      "superclass_id": 593,
      "superclass_name": "채소"
    },
    {
      "id": "d3be59c0-e3b2-4f83-af86-a57dcc0e9594",
      "class_id": 185,
      "class_name": "가지",
      "superclass_id": 593,
      "superclass_name": "채소"
    },
    {
      "id": "f1abdde1-ebd6-495c-a887-e5adf597735c",
      "class_id": 190,
      "class_name": "고추",
      "superclass_id": 593,
      "superclass_name": "채소"
    },
    {
      "id": "dc70ff65-8461-4280-a038-81538cbb2448",
      "class_id": 195,
      "class_name": "피망/파프리카",
      "superclass_id": 593,
      "superclass_name": "채소"
    },
    {
      "id": "9637282a-b300-4c6c-ae3a-305ca9d52e3d",
      "class_id": 176,
      "class_name": "오이",
      "superclass_id": 593,
      "superclass_name": "채소"
    },
    {
      "id": "cc5d0c2f-375d-467e-8031-e13524b411e7",
      "class_id": 181,
      "class_name": "호박",
      "superclass_id": 593,
      "superclass_name": "채소"
    },
    {
      "id": "45b1c9f2-3265-4aa5-989c-74ba1d7026ca",
      "class_id": 186,
      "class_name": "단호박",
      "superclass_id": 593,
      "superclass_name": "채소"
    },
    {
      "id": "b47a91e8-f9a1-4478-bf2b-ebf3d3236551",
      "class_id": 191,
      "class_name": "애호박",
      "superclass_id": 593,
      "superclass_name": "채소"
    },
    {
      "id": "dd3261d8-0a7a-479c-9fd8-08a555652a21",
      "class_id": 196,
      "class_name": "수세미",
      "superclass_id": 593,
      "superclass_name": "채소"
    },
    {
      "id": "64c0b661-f0c6-4fc3-9744-0db17180f334",
      "class_id": 177,
      "class_name": "무",
      "superclass_id": 593,
      "superclass_name": "채소"
    },
    {
      "id": "fc7029e8-c41d-4552-92e8-229430a6f5ea",
      "class_id": 182,
      "class_name": "당근",
      "superclass_id": 593,
      "superclass_name": "채소"
    },
    {
      "id": "d184d212-7c0b-44a9-b7ef-1b81645eb17b",
      "class_id": 187,
      "class_name": "감자",
      "superclass_id": 593,
      "superclass_name": "채소"
    },
    {
      "id": "d7569bf9-ac37-406e-a03a-dcdcbb2cffe0",
      "class_id": 192,
      "class_name": "우엉",
      "superclass_id": 593,
      "superclass_name": "채소"
    },
    {
      "id": "38e46589-90f1-4df2-a183-115440319fe9",
      "class_id": 197,
      "class_name": "연근",
      "superclass_id": 593,
      "superclass_name": "채소"
    },
    {
      "id": "891bab05-11ac-42f8-b55c-1384c409fd9c",
      "class_id": 178,
      "class_name": "도라지",
      "superclass_id": 593,
      "superclass_name": "채소"
    },
    {
      "id": "e6b1ec70-da30-44d7-be8c-b39f1f91b62f",
      "class_id": 183,
      "class_name": "고구마",
      "superclass_id": 593,
      "superclass_name": "채소"
    },
    {
      "id": "ba1c8e83-626a-4c8b-a3d1-53cdd44e0d8e",
      "class_id": 188,
      "class_name": "생강",
      "superclass_id": 593,
      "superclass_name": "채소"
    },
    {
      "id": "cf41494a-8645-4fcb-b5de-9fb8aec7e8a5",
      "class_id": 193,
      "class_name": "콜라비",
      "superclass_id": 593,
      "superclass_name": "채소"
    },
    {
      "id": "6e0011de-89cc-4948-bd67-858edabc432a",
      "class_id": 198,
      "class_name": "참마",
      "superclass_id": 593,
      "superclass_name": "채소"
    },
    {
      "id": "fa3dd3ac-f057-484a-a83d-00729e2c8672",
      "class_id": 179,
      "class_name": "와사비",
      "superclass_id": 593,
      "superclass_name": "채소"
    },
    {
      "id": "b0903806-52b2-490f-bf99-5f529a4acd42",
      "class_id": 184,
      "class_name": "죽순",
      "superclass_id": 593,
      "superclass_name": "채소"
    },
    {
      "id": "a22e24e9-11e8-414f-9cab-fced1b0eb66a",
      "class_id": 189,
      "class_name": "양파",
      "superclass_id": 593,
      "superclass_name": "채소"
    },
    {
      "id": "75f7aeae-9b1d-43cb-aaf6-600c9a825867",
      "class_id": 194,
      "class_name": "적양파",
      "superclass_id": 593,
      "superclass_name": "채소"
    },
    {
      "id": "5afb6c6b-c7b8-4f9c-89a0-fd2156b98cb3",
      "class_id": 199,
      "class_name": "마늘(깐것)",
      "superclass_id": 593,
      "superclass_name": "채소"
    },
    {
      "id": "a36f14c6-755c-4767-852d-f630f110f48a",
      "class_id": 200,
      "class_name": "통마늘(안깐것)",
      "superclass_id": 593,
      "superclass_name": "채소"
    },
    {
      "id": "96e3710e-47e2-4195-b057-89f2529fffac",
      "class_id": 201,
      "class_name": "상추",
      "superclass_id": 593,
      "superclass_name": "채소"
    },
    {
      "id": "e2a6c6fd-8baa-476e-836b-7cdeb9ea29fa",
      "class_id": 202,
      "class_name": "배추",
      "superclass_id": 593,
      "superclass_name": "채소"
    },
    {
      "id": "6b94c336-ee12-480f-b234-93ec1f1cf2fa",
      "class_id": 203,
      "class_name": "쑥갓",
      "superclass_id": 593,
      "superclass_name": "채소"
    },
    {
      "id": "75990b54-e8c3-4e20-91fe-b66f50bce209",
      "class_id": 204,
      "class_name": "양배추",
      "superclass_id": 593,
      "superclass_name": "채소"
    },
    {
      "id": "6e77b218-6a86-4bd1-b6e8-f6a30b58ef1e",
      "class_id": 205,
      "class_name": "양상추",
      "superclass_id": 593,
      "superclass_name": "채소"
    },
    {
      "id": "efb83dbc-47e4-46e6-8715-94a5f97629f6",
      "class_id": 206,
      "class_name": "브로콜리",
      "superclass_id": 593,
      "superclass_name": "채소"
    },
    {
      "id": "756261b6-7fc9-4c7c-a020-a5eab78a78e1",
      "class_id": 207,
      "class_name": "깻잎",
      "superclass_id": 593,
      "superclass_name": "채소"
    }
  ]
}