{
  "info": [
    {
      "name": "Data",
      "description": "Exported from Superb AI Suite",
      "url": "https://www.superb-ai.com",
      "date_created": "2022-01-22 13:26:53.734499"
    }
  ],
  "license": [
    {
      "name": "",
      "url": ""
    }
  ],
  "images": [
    {
      "id": "1466173_593",
      "width": 2800,
      "height": 2100,
      "file_name": "1466173_593.jpg",
      "license": "",
      "date_created": "2022-01-22 13:26:53.734584"
    }
  ],
  "annotations": [
    {
      "id": "e1d3975b-9ad1-4de7-b664-8ec80e5d584b",
      "image_id": "1466173_593",
      "category_id": 182,
      "segmentation": [
        {
          "x": 1563.566622076482,
          "y": 1014.5672342757772
        },
        {
          "x": 1574.0188014167866,
          "y": 1001.0041776211418
        },
        {
          "x": 1588.262585067394,
          "y": 997.975041709326
        },
        {
          "x": 1613.6437577006243,
          "y": 993.1770152728585
        },
        {
          "x": 1629.5659194023258,
          "y": 994.2044025565832
        },
        {
          "x": 1636.4805950884484,
          "y": 997.8053731276784
        },
        {
          "x": 1645.7851106906983,
          "y": 999.3767728185501
        },
        {
          "x": 1656.3931168339616,
          "y": 993.730575455862
        },
        {
          "x": 1656.0246093019289,
          "y": 1002.9064707130464
        },
        {
          "x": 1649.0678146650775,
          "y": 1012.9022708197585
        },
        {
          "x": 1635.5320532391645,
          "y": 1020.6709315431693
        },
        {
          "x": 1620.7035640178137,
          "y": 1033.4167185566043
        },
        {
          "x": 1602.6330251517647,
          "y": 1044.759365317836
        },
        {
          "x": 1591.853924640684,
          "y": 1048.3524025249133
        },
        {
          "x": 1576.6364231926361,
          "y": 1046.609148416434
        },
        {
          "x": 1567.9004135646958,
          "y": 1043.471830268012
        },
        {
          "x": 1551.4131522421817,
          "y": 1045.1152793284634
        },
        {
          "x": 1534.3710991242572,
          "y": 1047.9888436362323
        },
        {
          "x": 1531.4624504889086,
          "y": 1037.7230262147582
        },
        {
          "x": 1536.0820760892714,
          "y": 1032.076823304263
        },
        {
          "x": 1553.4149896324852,
          "y": 1022.6279093687266
        },
        {
          "x": 1563.566622076482,
          "y": 1014.5672342757772
        }
      ],
      "bbox": [
        1531.4624504889086,
        993.1770152728585,
        124.93066634505294,
        55.17538725205475
      ],
      "area": 6893.097895245539,
      "isSmallType": "Y"
    },
    {
      "id": "7fdac891-4f62-4aa7-a4c5-28a9c6da5b94",
      "image_id": "1466173_593",
      "category_id": 182,
      "segmentation": [
        {
          "x": 1725.4406567148365,
          "y": 1086.2896660408728
        },
        {
          "x": 1742.7829016694209,
          "y": 1091.6594938497776
        },
        {
          "x": 1755.721519341301,
          "y": 1095.138451501402
        },
        {
          "x": 1749.0487280402895,
          "y": 1098.7314887084794
        },
        {
          "x": 1735.2452738311108,
          "y": 1107.4061617939497
        },
        {
          "x": 1719.8710801222123,
          "y": 1117.4709377851607
        },
        {
          "x": 1702.8450601665118,
          "y": 1127.1507736394917
        },
        {
          "x": 1686.387579471963,
          "y": 1131.1172004492637
        },
        {
          "x": 1672.5765802452668,
          "y": 1133.5627625421766
        },
        {
          "x": 1668.2991655717665,
          "y": 1128.9431480311973
        },
        {
          "x": 1649.3527611281067,
          "y": 1132.8259361025553
        },
        {
          "x": 1643.1932751217748,
          "y": 1128.890699063768
        },
        {
          "x": 1641.1401094211262,
          "y": 1121.8681740001336
        },
        {
          "x": 1644.3909467921094,
          "y": 1116.7352652893965
        },
        {
          "x": 1650.379349526238,
          "y": 1113.6555222820768
        },
        {
          "x": 1659.7896729035529,
          "y": 1111.6023565786593
        },
        {
          "x": 1660.3029671026186,
          "y": 1103.2186215881686
        },
        {
          "x": 1665.4358758064332,
          "y": 1096.3747248144957
        },
        {
          "x": 1680.8346019178766,
          "y": 1090.2152332520495
        },
        {
          "x": 1691.5155062450933,
          "y": 1088.4770609347872
        },
        {
          "x": 1700.9258518136362,
          "y": 1089.332543870641
        },
        {
          "x": 1725.4406567148365,
          "y": 1086.2896660408728
        }
      ],
      "bbox": [
        1641.1401094211262,
        1086.2896660408728,
        114.58140992017479,
        47.273096501303826
      ],
      "area": 5416.618048411874,
      "isSmallType": "Y"
    },
    {
      "id": "dbfeb781-6445-4a87-9a70-4f9da91649ff",
      "image_id": "1466173_593",
      "category_id": 182,
      "segmentation": [
        {
          "x": 1743.3293606587204,
          "y": 1136.531382975177
        },
        {
          "x": 1783.2446780652176,
          "y": 1146.388393594034
        },
        {
          "x": 1798.8599128925637,
          "y": 1148.8010904782466
        },
        {
          "x": 1792.5293325184145,
          "y": 1159.4091077314308
        },
        {
          "x": 1773.8814222824735,
          "y": 1165.2180278213957
        },
        {
          "x": 1751.1467976907797,
          "y": 1169.5028432752104
        },
        {
          "x": 1723.4643281411097,
          "y": 1172.928059320373
        },
        {
          "x": 1701.1762132478405,
          "y": 1173.099153688421
        },
        {
          "x": 1685.4672648646847,
          "y": 1168.5140021545594
        },
        {
          "x": 1679.4539302859073,
          "y": 1162.500667567672
        },
        {
          "x": 1673.1221404898326,
          "y": 1160.9603966219079
        },
        {
          "x": 1663.4242409889714,
          "y": 1160.104913686054
        },
        {
          "x": 1659.6601094189225,
          "y": 1152.5766505358033
        },
        {
          "x": 1661.1999809205056,
          "y": 1144.8772930175044
        },
        {
          "x": 1676.2565182963147,
          "y": 1144.7061986494564
        },
        {
          "x": 1677.66944487817,
          "y": 1140.1473104339589
        },
        {
          "x": 1685.8867456474147,
          "y": 1133.812846586368
        },
        {
          "x": 1696.1852729251038,
          "y": 1130.89339081905
        },
        {
          "x": 1705.951366069584,
          "y": 1130.0370646165313
        },
        {
          "x": 1721.5992220020782,
          "y": 1132.692356005478
        },
        {
          "x": 1743.3293606587204,
          "y": 1136.531382975177
        }
      ],
      "bbox": [
        1659.6601094189225,
        1130.0370646165313,
        139.19980347364117,
        43.06208907188966
      ],
      "area": 5994.234335971471,
      "isSmallType": "Y"
    },
    {
      "id": "58cccf13-999e-400c-b94b-b6ac1e0f4fb1",
      "image_id": "1466173_593",
      "category_id": 182,
      "segmentation": [
        {
          "x": 1594.8206699109155,
          "y": 1218.849843182518
        },
        {
          "x": 1597.2863927311607,
          "y": 1204.4653449358143
        },
        {
          "x": 1603.9808537663062,
          "y": 1200.1756585074488
        },
        {
          "x": 1621.836592641008,
          "y": 1196.0954683672232
        },
        {
          "x": 1636.6517782211777,
          "y": 1198.3197284386888
        },
        {
          "x": 1676.4828799174456,
          "y": 1199.4854780291294
        },
        {
          "x": 1706.2252945879159,
          "y": 1205.7176736023816
        },
        {
          "x": 1714.0957686548759,
          "y": 1201.6113421955463
        },
        {
          "x": 1722.4546272674806,
          "y": 1205.4631956950418
        },
        {
          "x": 1725.3632759028292,
          "y": 1214.0180472448085
        },
        {
          "x": 1697.6595027742871,
          "y": 1226.1971590594792
        },
        {
          "x": 1683.9122367543837,
          "y": 1232.182399551691
        },
        {
          "x": 1663.3512651357203,
          "y": 1238.0918015221387
        },
        {
          "x": 1642.6230493272965,
          "y": 1250.7199750270581
        },
        {
          "x": 1623.7268636325825,
          "y": 1256.9492302625977
        },
        {
          "x": 1605.5051470258388,
          "y": 1253.8444555500696
        },
        {
          "x": 1599.6910341963583,
          "y": 1245.1760736777435
        },
        {
          "x": 1571.4828988380173,
          "y": 1258.6599187439551
        },
        {
          "x": 1555.6809137315056,
          "y": 1256.417905690072
        },
        {
          "x": 1548.3280611530697,
          "y": 1245.2424254495286
        },
        {
          "x": 1550.4251543895282,
          "y": 1231.5848119722925
        },
        {
          "x": 1560.8983488227411,
          "y": 1225.9336382267204
        },
        {
          "x": 1594.8206699109155,
          "y": 1218.849843182518
        }
      ],
      "bbox": [
        1548.3280611530697,
        1196.0954683672232,
        177.03521474975946,
        62.564450376731884
      ],
      "area": 11076.110908145398,
      "isSmallType": "Y"
    }
  ],
  "categories": [
    {
      "id": "d07035dc-9c6e-4a7a-8443-630b8ecce69e",
      "class_id": 175,
      "class_name": "토마토",
      "superclass_id": 593,
      "superclass_name": "채소"
    },
    {
      "id": "e5b10eb3-3a56-4893-90e0-b03d09056ab9",
      "class_id": 180,
      "class_name": "방울토마토",
      "superclass_id": 593,
      "superclass_name": "채소"
    },
    {
      "id": "d3be59c0-e3b2-4f83-af86-a57dcc0e9594",
      "class_id": 185,
      "class_name": "가지",
      "superclass_id": 593,
      "superclass_name": "채소"
    },
    {
      "id": "f1abdde1-ebd6-495c-a887-e5adf597735c",
      "class_id": 190,
      "class_name": "고추",
      "superclass_id": 593,
      "superclass_name": "채소"
    },
    {
      "id": "dc70ff65-8461-4280-a038-81538cbb2448",
      "class_id": 195,
      "class_name": "피망/파프리카",
      "superclass_id": 593,
      "superclass_name": "채소"
    },
    {
      "id": "9637282a-b300-4c6c-ae3a-305ca9d52e3d",
      "class_id": 176,
      "class_name": "오이",
      "superclass_id": 593,
      "superclass_name": "채소"
    },
    {
      "id": "cc5d0c2f-375d-467e-8031-e13524b411e7",
      "class_id": 181,
      "class_name": "호박",
      "superclass_id": 593,
      "superclass_name": "채소"
    },
    {
      "id": "45b1c9f2-3265-4aa5-989c-74ba1d7026ca",
      "class_id": 186,
      "class_name": "단호박",
      "superclass_id": 593,
      "superclass_name": "채소"
    },
    {
      "id": "b47a91e8-f9a1-4478-bf2b-ebf3d3236551",
      "class_id": 191,
      "class_name": "애호박",
      "superclass_id": 593,
      "superclass_name": "채소"
    },
    {
      "id": "dd3261d8-0a7a-479c-9fd8-08a555652a21",
      "class_id": 196,
      "class_name": "수세미",
      "superclass_id": 593,
      "superclass_name": "채소"
    },
    {
      "id": "64c0b661-f0c6-4fc3-9744-0db17180f334",
      "class_id": 177,
      "class_name": "무",
      "superclass_id": 593,
      "superclass_name": "채소"
    },
    {
      "id": "fc7029e8-c41d-4552-92e8-229430a6f5ea",
      "class_id": 182,
      "class_name": "당근",
      "superclass_id": 593,
      "superclass_name": "채소"
    },
    {
      "id": "d184d212-7c0b-44a9-b7ef-1b81645eb17b",
      "class_id": 187,
      "class_name": "감자",
      "superclass_id": 593,
      "superclass_name": "채소"
    },
    {
      "id": "d7569bf9-ac37-406e-a03a-dcdcbb2cffe0",
      "class_id": 192,
      "class_name": "우엉",
      "superclass_id": 593,
      "superclass_name": "채소"
    },
    {
      "id": "38e46589-90f1-4df2-a183-115440319fe9",
      "class_id": 197,
      "class_name": "연근",
      "superclass_id": 593,
      "superclass_name": "채소"
    },
    {
      "id": "891bab05-11ac-42f8-b55c-1384c409fd9c",
      "class_id": 178,
      "class_name": "도라지",
      "superclass_id": 593,
      "superclass_name": "채소"
    },
    {
      "id": "e6b1ec70-da30-44d7-be8c-b39f1f91b62f",
      "class_id": 183,
      "class_name": "고구마",
      "superclass_id": 593,
      "superclass_name": "채소"
    },
    {
      "id": "ba1c8e83-626a-4c8b-a3d1-53cdd44e0d8e",
      "class_id": 188,
      "class_name": "생강",
      "superclass_id": 593,
      "superclass_name": "채소"
    },
    {
      "id": "cf41494a-8645-4fcb-b5de-9fb8aec7e8a5",
      "class_id": 193,
      "class_name": "콜라비",
      "superclass_id": 593,
      "superclass_name": "채소"
    },
    {
      "id": "6e0011de-89cc-4948-bd67-858edabc432a",
      "class_id": 198,
      "class_name": "참마",
      "superclass_id": 593,
      "superclass_name": "채소"
    },
    {
      "id": "fa3dd3ac-f057-484a-a83d-00729e2c8672",
      "class_id": 179,
      "class_name": "와사비",
      "superclass_id": 593,
      "superclass_name": "채소"
    },
    {
      "id": "b0903806-52b2-490f-bf99-5f529a4acd42",
      "class_id": 184,
      "class_name": "죽순",
      "superclass_id": 593,
      "superclass_name": "채소"
    },
    {
      "id": "a22e24e9-11e8-414f-9cab-fced1b0eb66a",
      "class_id": 189,
      "class_name": "양파",
      "superclass_id": 593,
      "superclass_name": "채소"
    },
    {
      "id": "75f7aeae-9b1d-43cb-aaf6-600c9a825867",
      "class_id": 194,
      "class_name": "적양파",
      "superclass_id": 593,
      "superclass_name": "채소"
    },
    {
      "id": "5afb6c6b-c7b8-4f9c-89a0-fd2156b98cb3",
      "class_id": 199,
      "class_name": "마늘(깐것)",
      "superclass_id": 593,
      "superclass_name": "채소"
    },
    {
      "id": "a36f14c6-755c-4767-852d-f630f110f48a",
      "class_id": 200,
      "class_name": "통마늘(안깐것)",
      "superclass_id": 593,
      "superclass_name": "채소"
    },
    {
      "id": "96e3710e-47e2-4195-b057-89f2529fffac",
      "class_id": 201,
      "class_name": "상추",
      "superclass_id": 593,
      "superclass_name": "채소"
    },
    {
      "id": "e2a6c6fd-8baa-476e-836b-7cdeb9ea29fa",
      "class_id": 202,
      "class_name": "배추",
      "superclass_id": 593,
      "superclass_name": "채소"
    },
    {
      "id": "6b94c336-ee12-480f-b234-93ec1f1cf2fa",
      "class_id": 203,
      "class_name": "쑥갓",
      "superclass_id": 593,
      "superclass_name": "채소"
    },
    {
      "id": "75990b54-e8c3-4e20-91fe-b66f50bce209",
      "class_id": 204,
      "class_name": "양배추",
      "superclass_id": 593,
      "superclass_name": "채소"
    },
    {
      "id": "6e77b218-6a86-4bd1-b6e8-f6a30b58ef1e",
      "class_id": 205,
      "class_name": "양상추",
      "superclass_id": 593,
      "superclass_name": "채소"
    },
    {
      "id": "efb83dbc-47e4-46e6-8715-94a5f97629f6",
      "class_id": 206,
      "class_name": "브로콜리",
      "superclass_id": 593,
      "superclass_name": "채소"
    },
    {
      "id": "756261b6-7fc9-4c7c-a020-a5eab78a78e1",
      "class_id": 207,
      "class_name": "깻잎",
      "superclass_id": 593,
      "superclass_name": "채소"
    }
  ]
}